{
  "project_info": {
    "project_number": "198136499269",
    "project_id": "servimatch-6a63d",
    "storage_bucket": "servimatch-6a63d.appspot.com"
  },
  "client": [
    {
      "client_info": {
        "mobilesdk_app_id": "1:198136499269:android:9abfa811decfa3410aa72c",
        "android_client_info": {
          "package_name": "ar.com.utn.devmobile.servimatch"
        }
      },
      "oauth_client": [],
      "api_key": [
        {
          "current_key": "AIzaSyD1mtVGotIhVchn2BhHVcYDaqGmbZmjoyw"
        }
      ],
      "services": {
        "appinvite_service": {
          "other_platform_oauth_client": []
        }
      }
    }
  ],
  "configuration_version": "1"
}